spinq/__init__.py
spinq/CHANGELOG.md
spinq/dicts.py
spinq/LICENSE
spinq/lists.py
spinq/poetry.lock
spinq-1.4.0.dist-info/METADATA
spinq-1.4.0.dist-info/WHEEL
spinq-1.4.0.dist-info/RECORD
