Metadata-Version: 2.4
Name: spinq
Version: 1.4.0
Summary: Simple LINQ in Python
License: MIT
Author: Kostiantyn Chomakov
Author-email: kostiantyn.chomakov@gmail.com
Requires-Python: >=3.13,<4.0
Classifier: License :: OSI Approved :: MIT License
Classifier: Operating System :: OS Independent
Classifier: Programming Language :: Python :: 3
Classifier: Programming Language :: Python :: 3.13
Classifier: Programming Language :: Python :: 3.14
Project-URL: Homepage, https://github.com/takinosaji/partial-injector
Project-URL: Repository, https://github.com/takinosaji/partial-injector
